sage_tokenizer/HFEncoding.py
sage_tokenizer/SaGeVocabBuilder.py
sage_tokenizer/Word2VecParams.py
sage_tokenizer/__init__.py
sage_tokenizer/embeddings.py
sage_tokenizer/model.py
sage_tokenizer/utils.py
sage_tokenizer-2.0.0.dist-info/METADATA
sage_tokenizer-2.0.0.dist-info/WHEEL
sage_tokenizer-2.0.0.dist-info/licenses/LICENSE
sage_tokenizer-2.0.0.dist-info/RECORD
