Metadata-Version: 2.3
Name: sage-tokenizer
Version: 2.0.0
Summary: SaGe subword tokenizer - version 2.0
Project-URL: Homepage, https://github.com/MeLeLBGU/SaGe
Project-URL: Issues, https://github.com/MeLeLBGU/SaGe/issues
Author: Shaked Yehezkel, Kensho Technologies, Bar Gazit, Yuval Pinter
License-File: LICENSE
Classifier: License :: OSI Approved :: MIT License
Classifier: Operating System :: OS Independent
Classifier: Programming Language :: Python :: 3
Requires-Python: >=3.8
Requires-Dist: gensim==4.3.2
Requires-Dist: scipy==1.12.0
